setup.py
src/nt3irisadapter/__init__.py
src/nt3irisadapter/server.py
src/nt3irisadapter.egg-info/PKG-INFO
src/nt3irisadapter.egg-info/SOURCES.txt
src/nt3irisadapter.egg-info/dependency_links.txt
src/nt3irisadapter.egg-info/requires.txt
src/nt3irisadapter.egg-info/top_level.txt
src/nt3irisadapter/services/__init__.py
src/nt3irisadapter/services/logic/__init__.py
src/nt3irisadapter/services/logic/helpers.py
src/nt3irisadapter/services/model/__init__.py
src/nt3irisadapter/services/model/pos_service_pb2.py
src/nt3irisadapter/services/model/pos_service_pb2_grpc.py
src/nt3irisadapter/services/model/service_config.py
src/nt3irisadapter/services/persistance/__init__.py
src/nt3irisadapter/services/persistance/authorization.py
src/nt3irisadapter/services/persistance/echo.py
src/nt3irisadapter/services/server_grpc/__init__.py
src/nt3irisadapter/services/server_grpc/server_grpc.py