Metadata-Version: 2.1
Name: nt3irisadapter
Version: 0.0.6
Summary: IRIS Adapter for NovaTouch 3
Home-page: UNKNOWN
Author: novacom software GmbH
License: UNKNOWN
Platform: UNKNOWN
